{"paths": {"admin/js/vendor/select2/i18n/af.js": "admin/js/vendor/select2/i18n/af.4f6fcd73488c.js", "admin/js/vendor/select2/i18n/ar.js": "admin/js/vendor/select2/i18n/ar.65aa8e36bf5d.js", "admin/js/vendor/select2/i18n/az.js": "admin/js/vendor/select2/i18n/az.270c257daf81.js", "admin/js/vendor/select2/i18n/bg.js": "admin/js/vendor/select2/i18n/bg.39b8be30d4f0.js", "admin/js/vendor/select2/i18n/bn.js": "admin/js/vendor/select2/i18n/bn.6d42b4dd5665.js", "admin/js/vendor/select2/i18n/bs.js": "admin/js/vendor/select2/i18n/bs.91624382358e.js", "admin/js/vendor/select2/i18n/ca.js": "admin/js/vendor/select2/i18n/ca.a166b745933a.js", "admin/js/vendor/select2/i18n/cs.js": "admin/js/vendor/select2/i18n/cs.4f43e8e7d33a.js", "admin/js/vendor/select2/i18n/da.js": "admin/js/vendor/select2/i18n/da.766346afe4dd.js", "admin/js/vendor/select2/i18n/de.js": "admin/js/vendor/select2/i18n/de.8a1c222b0204.js", "admin/js/vendor/select2/i18n/dsb.js": "admin/js/vendor/select2/i18n/dsb.56372c92d2f1.js", "admin/js/vendor/select2/i18n/el.js": "admin/js/vendor/select2/i18n/el.27097f071856.js", "admin/js/vendor/select2/i18n/en.js": "admin/js/vendor/select2/i18n/en.cf932ba09a98.js", "admin/js/vendor/select2/i18n/es.js": "admin/js/vendor/select2/i18n/es.66dbc2652fb1.js", "admin/js/vendor/select2/i18n/et.js": "admin/js/vendor/select2/i18n/et.2b96fd98289d.js", "admin/js/vendor/select2/i18n/eu.js": "admin/js/vendor/select2/i18n/eu.adfe5c97b72c.js", "admin/js/vendor/select2/i18n/fa.js": "admin/js/vendor/select2/i18n/fa.3b5bd1961cfd.js", "admin/js/vendor/select2/i18n/fi.js": "admin/js/vendor/select2/i18n/fi.614ec42aa9ba.js", "admin/js/vendor/select2/i18n/fr.js": "admin/js/vendor/select2/i18n/fr.05e0542fcfe6.js", "admin/js/vendor/select2/i18n/gl.js": "admin/js/vendor/select2/i18n/gl.d99b1fedaa86.js", "admin/js/vendor/select2/i18n/he.js": "admin/js/vendor/select2/i18n/he.e420ff6cd3ed.js", "admin/js/vendor/select2/i18n/hi.js": "admin/js/vendor/select2/i18n/hi.70640d41628f.js", "admin/js/vendor/select2/i18n/hr.js": "admin/js/vendor/select2/i18n/hr.a2b092cc1147.js", "admin/js/vendor/select2/i18n/hsb.js": "admin/js/vendor/select2/i18n/hsb.fa3b55265efe.js", "admin/js/vendor/select2/i18n/hu.js": "admin/js/vendor/select2/i18n/hu.6ec6039cb8a3.js", "admin/js/vendor/select2/i18n/hy.js": "admin/js/vendor/select2/i18n/hy.c7babaeef5a6.js", "admin/js/vendor/select2/i18n/id.js": "admin/js/vendor/select2/i18n/id.04debded514d.js", "admin/js/vendor/select2/i18n/is.js": "admin/js/vendor/select2/i18n/is.3ddd9a6a97e9.js", "admin/js/vendor/select2/i18n/it.js": "admin/js/vendor/select2/i18n/it.be4fe8d365b5.js", "admin/js/vendor/select2/i18n/ja.js": "admin/js/vendor/select2/i18n/ja.170ae885d74f.js", "admin/js/vendor/select2/i18n/ka.js": "admin/js/vendor/select2/i18n/ka.2083264a54f0.js", "admin/js/vendor/select2/i18n/km.js": "admin/js/vendor/select2/i18n/km.c23089cb06ca.js", "admin/js/vendor/select2/i18n/ko.js": "admin/js/vendor/select2/i18n/ko.e7be6c20e673.js", "admin/js/vendor/select2/i18n/lt.js": "admin/js/vendor/select2/i18n/lt.23c7ce903300.js", "admin/js/vendor/select2/i18n/lv.js": "admin/js/vendor/select2/i18n/lv.08e62128eac1.js", "admin/js/vendor/select2/i18n/mk.js": "admin/js/vendor/select2/i18n/mk.dabbb9087130.js", "admin/js/vendor/select2/i18n/ms.js": "admin/js/vendor/select2/i18n/ms.4ba82c9a51ce.js", "admin/js/vendor/select2/i18n/nb.js": "admin/js/vendor/select2/i18n/nb.da2fce143f27.js", "admin/js/vendor/select2/i18n/ne.js": "admin/js/vendor/select2/i18n/ne.3d79fd3f08db.js", "admin/js/vendor/select2/i18n/nl.js": "admin/js/vendor/select2/i18n/nl.997868a37ed8.js", "admin/js/vendor/select2/i18n/pl.js": "admin/js/vendor/select2/i18n/pl.6031b4f16452.js", "admin/js/vendor/select2/i18n/ps.js": "admin/js/vendor/select2/i18n/ps.38dfa47af9e0.js", "admin/js/vendor/select2/i18n/pt-BR.js": "admin/js/vendor/select2/i18n/pt-BR.e1b294433e7f.js", "admin/js/vendor/select2/i18n/pt.js": "admin/js/vendor/select2/i18n/pt.33b4a3b44d43.js", "admin/js/vendor/select2/i18n/ro.js": "admin/js/vendor/select2/i18n/ro.f75cb460ec3b.js", "admin/js/vendor/select2/i18n/ru.js": "admin/js/vendor/select2/i18n/ru.934aa95f5b5f.js", "admin/js/vendor/select2/i18n/sk.js": "admin/js/vendor/select2/i18n/sk.33d02cef8d11.js", "admin/js/vendor/select2/i18n/sl.js": "admin/js/vendor/select2/i18n/sl.131a78bc0752.js", "admin/js/vendor/select2/i18n/sq.js": "admin/js/vendor/select2/i18n/sq.5636b60d29c9.js", "admin/js/vendor/select2/i18n/sr-Cyrl.js": "admin/js/vendor/select2/i18n/sr-Cyrl.f254bb8c4c7c.js", "admin/js/vendor/select2/i18n/sr.js": "admin/js/vendor/select2/i18n/sr.5ed85a48f483.js", "admin/js/vendor/select2/i18n/sv.js": "admin/js/vendor/select2/i18n/sv.7a9c2f71e777.js", "admin/js/vendor/select2/i18n/th.js": "admin/js/vendor/select2/i18n/th.f38c20b0221b.js", "admin/js/vendor/select2/i18n/tk.js": "admin/js/vendor/select2/i18n/tk.7c572a68c78f.js", "admin/js/vendor/select2/i18n/tr.js": "admin/js/vendor/select2/i18n/tr.b5a0643d1545.js", "admin/js/vendor/select2/i18n/uk.js": "admin/js/vendor/select2/i18n/uk.8cede7f4803c.js", "admin/js/vendor/select2/i18n/vi.js": "admin/js/vendor/select2/i18n/vi.097a5b75b3e1.js", "admin/js/vendor/select2/i18n/zh-CN.js": "admin/js/vendor/select2/i18n/zh-CN.2cff662ec5f9.js", "admin/js/vendor/select2/i18n/zh-TW.js": "admin/js/vendor/select2/i18n/zh-TW.04554a227c2b.js", "admin/css/vendor/select2/LICENSE-SELECT2.md": "admin/css/vendor/select2/LICENSE-SELECT2.f94142512c91.md", "admin/css/vendor/select2/select2.css": "admin/css/vendor/select2/select2.a2194c262648.css", "admin/css/vendor/select2/select2.min.css": "admin/css/vendor/select2/select2.min.9f54e6414f87.css", "admin/js/vendor/jquery/jquery.js": "admin/js/vendor/jquery/jquery.23c7c5d2d131.js", "admin/js/vendor/jquery/jquery.min.js": "admin/js/vendor/jquery/jquery.min.dc5e7f18c8d3.js", "admin/js/vendor/jquery/LICENSE.txt": "admin/js/vendor/jquery/LICENSE.75308107741f.txt", "admin/js/vendor/select2/LICENSE.md": "admin/js/vendor/select2/LICENSE.f94142512c91.md", "admin/js/vendor/select2/select2.full.js": "admin/js/vendor/select2/select2.full.c2afdeda3058.js", "admin/js/vendor/select2/select2.full.min.js": "admin/js/vendor/select2/select2.full.min.fcd7500d8e13.js", "admin/js/vendor/xregexp/LICENSE.txt": "admin/js/vendor/xregexp/LICENSE.bf79e414957a.txt", "admin/js/vendor/xregexp/xregexp.js": "admin/js/vendor/xregexp/xregexp.efda034b9537.js", "admin/js/vendor/xregexp/xregexp.min.js": "admin/js/vendor/xregexp/xregexp.min.b0439563a5d3.js", "admin/img/gis/move_vertex_off.svg": "admin/img/gis/move_vertex_off.7a23bf31ef8a.svg", "admin/img/gis/move_vertex_on.svg": "admin/img/gis/move_vertex_on.0047eba25b67.svg", "admin/js/admin/DateTimeShortcuts.js": "admin/js/admin/DateTimeShortcuts.29d0b1965c07.js", "admin/js/admin/RelatedObjectLookups.js": "admin/js/admin/RelatedObjectLookups.d7e023e6523b.js", "Images/index/About.jfif": "Images/index/About.6a41b3180722.jfif", "Images/index/About2.jfif": "Images/index/About2.f8145e3efdaa.jfif", "Images/index/accessories category.jfif": "Images/index/accessories category.e505efb2bebd.jfif", "Images/index/accessories front.jfif": "Images/index/accessories front.b76e5f96cdef.jfif", "Images/index/accessories slide.jfif": "Images/index/accessories slide.20c65bdaf0f9.jfif", "Images/index/background slide.jfif": "Images/index/background slide.d814c91fceef.jfif", "Images/index/banner fishing.jpg": "Images/index/banner fishing.71a513374cef.jpg", "Images/index/BC rod front.jfif": "Images/index/BC rod front.beac6b5778e5.jfif", "Images/index/img-1.jfif": "Images/index/img-1.f79a0d823181.jfif", "Images/index/img-2.jfif": "Images/index/img-2.32c78d2125fa.jfif", "Images/index/line category.jfif": "Images/index/line category.3e3309022b91.jfif", "Images/index/Line front.jfif": "Images/index/Line front.bb61f4f8301f.jfif", "Images/index/line slide.jfif": "Images/index/line slide.8140b983b8c9.jfif", "Images/index/lure category.jfif": "Images/index/lure category.70a290329eda.jfif", "Images/index/lure slide.jfif": "Images/index/lure slide.1aea783af41d.jfif", "Images/index/lures front.jfif": "Images/index/lures front.b7a0acc83658.jfif", "Images/index/reel category.jfif": "Images/index/reel category.4c02a1d8bf02.jfif", "Images/index/Reel front.jfif": "Images/index/Reel front.5fc9e329bfea.jfif", "Images/index/reel slide.jfif": "Images/index/reel slide.df52aa673710.jfif", "Images/index/rod category.jfif": "Images/index/rod category.207bcfa47e0d.jfif", "Images/index/rod slide.jfif": "Images/index/rod slide.af005afcf3de.jfif", "Images/index/tackle front 1.jpg": "Images/index/tackle front 1.30e5163868be.jpg", "Images/index/tackle front 2.jpg": "Images/index/tackle front 2.1b3f2915ecbb.jpg", "Images/index/tackle front 3.jpg": "Images/index/tackle front 3.d7acca7ee9a6.jpg", "Images/index/tackle front 4.jpg": "Images/index/tackle front 4.ec86de1f450e.jpg", "Images/index/tackle front 5.jpg": "Images/index/tackle front 5.c35687c080c2.jpg", "Images/index/tackle front 6.jpeg": "Images/index/tackle front 6.326ed2d2b485.jpeg", "Images/index/tackle front 6.jpg": "Images/index/tackle front 6.0bb3e1b5ee05.jpg", "Images/index/tackle front 7.jfif": "Images/index/tackle front 7.d55cbffc6d59.jfif", "Images/index/tackle front 8.jfif": "Images/index/tackle front 8.6363440d05f5.jfif", "Images/index/Terminal tackle front.jfif": "Images/index/Terminal tackle front.1d55e035eb0a.jfif", "admin/css/autocomplete.css": "admin/css/autocomplete.781713f30664.css", "admin/css/base.css": "admin/css/base.efb520c4bb7c.css", "admin/css/changelists.css": "admin/css/changelists.403ad0c24fa6.css", "admin/css/dashboard.css": "admin/css/dashboard.be83f13e4369.css", "admin/css/fonts.css": "admin/css/fonts.168bab448fee.css", "admin/css/forms.css": "admin/css/forms.6230fc2a74ac.css", "admin/css/login.css": "admin/css/login.d2a477e04949.css", "admin/css/nav_sidebar.css": "admin/css/nav_sidebar.59831780a474.css", "admin/css/responsive.css": "admin/css/responsive.0ed741a014cf.css", "admin/css/responsive_rtl.css": "admin/css/responsive_rtl.e13ae754cceb.css", "admin/css/rtl.css": "admin/css/rtl.775b89eb85cb.css", "admin/css/widgets.css": "admin/css/widgets.b12c020d05e0.css", "admin/fonts/LICENSE.txt": "admin/fonts/LICENSE.d273d63619c9.txt", "admin/fonts/README.txt": "admin/fonts/README.ab99e6b541ea.txt", "admin/fonts/Roboto-Bold-webfont.woff": "admin/fonts/Roboto-Bold-webfont.50d75e48e0a3.woff", "admin/fonts/Roboto-Light-webfont.woff": "admin/fonts/Roboto-Light-webfont.c73eb1ceba33.woff", "admin/fonts/Roboto-Regular-webfont.woff": "admin/fonts/Roboto-Regular-webfont.35b07eb2f871.woff", "admin/img/calendar-icons.svg": "admin/img/calendar-icons.39b290681a8b.svg", "admin/img/icon-addlink.svg": "admin/img/icon-addlink.d519b3bab011.svg", "admin/img/icon-alert.svg": "admin/img/icon-alert.034cc7d8a67f.svg", "admin/img/icon-calendar.svg": "admin/img/icon-calendar.ac7aea671bea.svg", "admin/img/icon-changelink.svg": "admin/img/icon-changelink.18d2fd706348.svg", "admin/img/icon-clock.svg": "admin/img/icon-clock.e1d4dfac3f2b.svg", "admin/img/icon-deletelink.svg": "admin/img/icon-deletelink.564ef9dc3854.svg", "admin/img/icon-no.svg": "admin/img/icon-no.439e821418cd.svg", "admin/img/icon-unknown-alt.svg": "admin/img/icon-unknown-alt.81536e128bb6.svg", "admin/img/icon-unknown.svg": "admin/img/icon-unknown.a18cb4398978.svg", "admin/img/icon-viewlink.svg": "admin/img/icon-viewlink.41eb31f7826e.svg", "admin/img/icon-yes.svg": "admin/img/icon-yes.d2f9f035226a.svg", "admin/img/inline-delete.svg": "admin/img/inline-delete.fec1b761f254.svg", "admin/img/LICENSE": "admin/img/LICENSE.2c54f4e1ca1c", "admin/img/README.txt": "admin/img/README.a70711a38d87.txt", "admin/img/search.svg": "admin/img/search.7cf54ff789c6.svg", "admin/img/selector-icons.svg": "admin/img/selector-icons.b4555096cea2.svg", "admin/img/sorting-icons.svg": "admin/img/sorting-icons.3a097b59f104.svg", "admin/img/tooltag-add.svg": "admin/img/tooltag-add.e59d620a9742.svg", "admin/img/tooltag-arrowright.svg": "admin/img/tooltag-arrowright.bbfb788a849e.svg", "admin/js/actions.js": "admin/js/actions.9fe89b71cbba.js", "admin/js/actions.min.js": "admin/js/actions.min.5f3040a29159.js", "admin/js/autocomplete.js": "admin/js/autocomplete.618a7ebf39d8.js", "admin/js/calendar.js": "admin/js/calendar.b4dcf6f850fe.js", "admin/js/cancel.js": "admin/js/cancel.50e7573ea4a7.js", "admin/js/change_form.js": "admin/js/change_form.9d8ca4f96b75.js", "admin/js/collapse.js": "admin/js/collapse.f84e7410290f.js", "admin/js/collapse.min.js": "admin/js/collapse.min.10ac29832e2c.js", "admin/js/core.js": "admin/js/core.fae39a43def0.js", "admin/js/inlines.js": "admin/js/inlines.7596b7fd289e.js", "admin/js/inlines.min.js": "admin/js/inlines.min.599e296e4c24.js", "admin/js/jquery.init.js": "admin/js/jquery.init.b7781a0897fc.js", "admin/js/nav_sidebar.js": "admin/js/nav_sidebar.7605597ddf52.js", "admin/js/popup_response.js": "admin/js/popup_response.c6cc78ea5551.js", "admin/js/prepopulate.js": "admin/js/prepopulate.bd2361dfd64d.js", "admin/js/prepopulate.min.js": "admin/js/prepopulate.min.5f7f80162256.js", "admin/js/prepopulate_init.js": "admin/js/prepopulate_init.e056047b7a7e.js", "admin/js/SelectBox.js": "admin/js/SelectBox.46d59670a7a7.js", "admin/js/SelectFilter2.js": "admin/js/SelectFilter2.d250dcb52a9a.js", "admin/js/urlify.js": "admin/js/urlify.3cabcb7a9073.js", "css/brand.css": "css/brand.d41d8cd98f00.css", "css/cart.css": "css/cart.fc1033af9112.css", "css/login.css": "css/login.996762b9ed2b.css", "css/main.css": "css/main.8fd97c187b03.css", "css/OFL.txt": "css/OFL.1be2e7edc99b.txt", "css/Page.css": "css/Page.6e23b5c4a10b.css", "css/register.css": "css/register.996762b9ed2b.css", "css/Try & Error.bsdesign": "css/Try & Error.422b93c3104a.bsdesign", "css/vendor login.css": "css/vendor login.1497a6d9457a.css", "css/vendor register.css": "css/vendor register.f1453bd1c75a.css", "Images/About2.jfif": "Images/About2.f8145e3efdaa.jfif", "Images/arrow-down.png": "Images/arrow-down.f2fb016116bd.png", "Images/arrow-down_DQnjXcI.png": "Images/arrow-down_DQnjXcI.f2fb016116bd.png", "Images/arrow-up.png": "Images/arrow-up.25d43b259b74.png", "Images/BC_rod_front.jfif": "Images/BC_rod_front.beac6b5778e5.jfif", "Images/BC_rod_front_1mJKz8Y.jfif": "Images/BC_rod_front_1mJKz8Y.beac6b5778e5.jfif", "Images/BC_rod_front_90gMuJA.jfif": "Images/BC_rod_front_90gMuJA.beac6b5778e5.jfif", "Images/BC_rod_front_OflXEv7.jfif": "Images/BC_rod_front_OflXEv7.beac6b5778e5.jfif", "Images/BC_rod_front_rBvB3Kd.jfif": "Images/BC_rod_front_rBvB3Kd.beac6b5778e5.jfif", "Images/img-1.jfif": "Images/img-1.01ab6ffa4017.jfif", "Images/img-10.jfif": "Images/img-10.2abb269d7adc.jfif", "Images/img-10_0xDhHKi.jfif": "Images/img-10_0xDhHKi.991dbba203a4.jfif", "Images/img-10_2o3sN3e.jfif": "Images/img-10_2o3sN3e.2abb269d7adc.jfif", "Images/img-10_5JSHEUQ.jfif": "Images/img-10_5JSHEUQ.2abb269d7adc.jfif", "Images/img-10_5Qam5yx.jfif": "Images/img-10_5Qam5yx.df1a23a66cd4.jfif", "Images/img-10_9nCE5dc.jfif": "Images/img-10_9nCE5dc.df1a23a66cd4.jfif", "Images/img-10_cqsuNhm.jfif": "Images/img-10_cqsuNhm.991dbba203a4.jfif", "Images/img-10_D8z1KWc.jfif": "Images/img-10_D8z1KWc.851894516d4a.jfif", "Images/img-10_e2DTToL.jfif": "Images/img-10_e2DTToL.991dbba203a4.jfif", "Images/img-10_FzgjpfF.jfif": "Images/img-10_FzgjpfF.2abb269d7adc.jfif", "Images/img-10_iOO0R4z.jfif": "Images/img-10_iOO0R4z.851894516d4a.jfif", "Images/img-10_pBNBIKU.jfif": "Images/img-10_pBNBIKU.2abb269d7adc.jfif", "Images/img-10_tnx4JkH.jfif": "Images/img-10_tnx4JkH.851894516d4a.jfif", "Images/img-10_yuRd6Eu.jfif": "Images/img-10_yuRd6Eu.991dbba203a4.jfif", "Images/img-11.jfif": "Images/img-11.204a78f40bde.jfif", "Images/img-11.png": "Images/img-11.f765d4839f80.png", "Images/img-11_2eOCJak.jfif": "Images/img-11_2eOCJak.99b382b8e3d8.jfif", "Images/img-11_aIUd1YJ.jfif": "Images/img-11_aIUd1YJ.204a78f40bde.jfif", "Images/img-11_bEmww03.jfif": "Images/img-11_bEmww03.204a78f40bde.jfif", "Images/img-11_cDWIuf5.jfif": "Images/img-11_cDWIuf5.99b382b8e3d8.jfif", "Images/img-11_DvKyl9R.png": "Images/img-11_DvKyl9R.f765d4839f80.png", "Images/img-11_ff7w2AW.jfif": "Images/img-11_ff7w2AW.3e7fcb76dd65.jfif", "Images/img-11_SEeSOON.jfif": "Images/img-11_SEeSOON.99b382b8e3d8.jfif", "Images/img-11_vZ5eLlp.jfif": "Images/img-11_vZ5eLlp.4c120f8a8ae1.jfif", "Images/img-11_wjQtHWI.jfif": "Images/img-11_wjQtHWI.4c120f8a8ae1.jfif", "Images/img-11_YAXxjRM.jfif": "Images/img-11_YAXxjRM.3e7fcb76dd65.jfif", "Images/img-11_yOeQvdO.jfif": "Images/img-11_yOeQvdO.99b382b8e3d8.jfif", "Images/img-11_Zx4q8vU.jfif": "Images/img-11_Zx4q8vU.3e7fcb76dd65.jfif", "Images/img-12.jfif": "Images/img-12.ae61d5f5644c.jfif", "Images/img-12_6Om2lBM.jfif": "Images/img-12_6Om2lBM.171538b0640f.jfif", "Images/img-12_CaaGOMj.jfif": "Images/img-12_CaaGOMj.a36ae5ba93f6.jfif", "Images/img-12_fLTrOi1.jfif": "Images/img-12_fLTrOi1.a36ae5ba93f6.jfif", "Images/img-12_hoXNZny.jfif": "Images/img-12_hoXNZny.6005a0379e49.jfif", "Images/img-12_HTjFILg.jfif": "Images/img-12_HTjFILg.67a944b08c7c.jfif", "Images/img-12_IUp5b9L.jfif": "Images/img-12_IUp5b9L.a36ae5ba93f6.jfif", "Images/img-12_LwMtF1w.jfif": "Images/img-12_LwMtF1w.ae61d5f5644c.jfif", "Images/img-12_MYqf6YN.jfif": "Images/img-12_MYqf6YN.ae61d5f5644c.jfif", "Images/img-12_nCRSpP4.jfif": "Images/img-12_nCRSpP4.171538b0640f.jfif", "Images/img-12_NnYUjFq.jfif": "Images/img-12_NnYUjFq.67a944b08c7c.jfif", "Images/img-12_nY6nYbK.jfif": "Images/img-12_nY6nYbK.a36ae5ba93f6.jfif", "Images/img-12_oE0CiO7.jfif": "Images/img-12_oE0CiO7.ae61d5f5644c.jfif", "Images/img-12_rTHbb4J.jfif": "Images/img-12_rTHbb4J.6005a0379e49.jfif", "Images/img-12_WCwiQRw.jfif": "Images/img-12_WCwiQRw.171538b0640f.jfif", "Images/img-12_yszLQi0.jfif": "Images/img-12_yszLQi0.171538b0640f.jfif", "Images/img-1_06ndmup.jfif": "Images/img-1_06ndmup.1d7c86f324b5.jfif", "Images/img-1_0AlzE1T.jfif": "Images/img-1_0AlzE1T.01ab6ffa4017.jfif", "Images/img-1_7kOyyqU.jfif": "Images/img-1_7kOyyqU.3dd290dd53cb.jfif", "Images/img-1_8CuZoAO.jfif": "Images/img-1_8CuZoAO.1d7c86f324b5.jfif", "Images/img-1_8ijF6rt.jfif": "Images/img-1_8ijF6rt.3dd290dd53cb.jfif", "Images/img-1_abpv2IA.jfif": "Images/img-1_abpv2IA.1546e563dd2d.jfif", "Images/img-1_aiJN8tM.jfif": "Images/img-1_aiJN8tM.dd298f06b32f.jfif", "Images/img-1_cbAI6a4.jfif": "Images/img-1_cbAI6a4.01ab6ffa4017.jfif", "Images/img-1_eGg8W5z.jfif": "Images/img-1_eGg8W5z.01ab6ffa4017.jfif", "Images/img-1_esjqrSU.jfif": "Images/img-1_esjqrSU.01ab6ffa4017.jfif", "Images/img-1_fEOaf1u.jfif": "Images/img-1_fEOaf1u.dd298f06b32f.jfif", "Images/img-1_gATeF4P.jfif": "Images/img-1_gATeF4P.1546e563dd2d.jfif", "Images/img-1_GoKDDnj.jfif": "Images/img-1_GoKDDnj.1546e563dd2d.jfif", "Images/img-1_IskqpMT.jfif": "Images/img-1_IskqpMT.01ab6ffa4017.jfif", "Images/img-1_J3FPrw9.jfif": "Images/img-1_J3FPrw9.01ab6ffa4017.jfif", "Images/img-1_lwqikMP.jfif": "Images/img-1_lwqikMP.1d7c86f324b5.jfif", "Images/img-1_O0nDgIN.jfif": "Images/img-1_O0nDgIN.01ab6ffa4017.jfif", "Images/img-1_oCIF33H.jfif": "Images/img-1_oCIF33H.01ab6ffa4017.jfif", "Images/img-1_PYlmE39.jfif": "Images/img-1_PYlmE39.1d7c86f324b5.jfif", "Images/img-1_r4SBiqK.jfif": "Images/img-1_r4SBiqK.dd298f06b32f.jfif", "Images/img-1_RhbQcdq.jfif": "Images/img-1_RhbQcdq.01ab6ffa4017.jfif", "Images/img-1_T9Ne4nO.jfif": "Images/img-1_T9Ne4nO.1d7c86f324b5.jfif", "Images/img-1_teIJnRY.jfif": "Images/img-1_teIJnRY.dd298f06b32f.jfif", "Images/img-1_vKIxFuX.jfif": "Images/img-1_vKIxFuX.01ab6ffa4017.jfif", "Images/img-1_W2FakeF.jfif": "Images/img-1_W2FakeF.01ab6ffa4017.jfif", "Images/img-1_WFs4uYS.jfif": "Images/img-1_WFs4uYS.01ab6ffa4017.jfif", "Images/img-1_WIwYLyo.jfif": "Images/img-1_WIwYLyo.1546e563dd2d.jfif", "Images/img-1_wM5V7nP.jfif": "Images/img-1_wM5V7nP.01ab6ffa4017.jfif", "Images/img-1_XK72nHR.jfif": "Images/img-1_XK72nHR.3dd290dd53cb.jfif", "Images/img-1_yPgtItN.jfif": "Images/img-1_yPgtItN.3dd290dd53cb.jfif", "Images/img-2.jfif": "Images/img-2.a98aa762f9e7.jfif", "Images/img-2_125BHV7.jfif": "Images/img-2_125BHV7.3e3309022b91.jfif", "Images/img-2_7F0ifIB.jfif": "Images/img-2_7F0ifIB.3bf05c122ba4.jfif", "Images/img-2_BXLkrGY.jfif": "Images/img-2_BXLkrGY.3bf05c122ba4.jfif", "Images/img-2_CevYrrh.jfif": "Images/img-2_CevYrrh.a98aa762f9e7.jfif", "Images/img-2_eozDYoQ.jfif": "Images/img-2_eozDYoQ.a98aa762f9e7.jfif", "Images/img-2_ieRwOP7.jfif": "Images/img-2_ieRwOP7.3bf05c122ba4.jfif", "Images/img-2_IrQBb7L.jfif": "Images/img-2_IrQBb7L.c4edcc0598e3.jfif", "Images/img-2_j1vbQmR.jfif": "Images/img-2_j1vbQmR.cb1bc54e7667.jfif", "Images/img-2_jxxb7wa.jfif": "Images/img-2_jxxb7wa.cb1bc54e7667.jfif", "Images/img-2_KVa9qYq.jfif": "Images/img-2_KVa9qYq.c4edcc0598e3.jfif", "Images/img-2_l8P9WyH.jfif": "Images/img-2_l8P9WyH.3e3309022b91.jfif", "Images/img-2_MaYkpiQ.jfif": "Images/img-2_MaYkpiQ.c4edcc0598e3.jfif", "Images/img-2_OaO574R.jfif": "Images/img-2_OaO574R.cb1bc54e7667.jfif", "Images/img-2_TJ3YDhw.jfif": "Images/img-2_TJ3YDhw.3e3309022b91.jfif", "Images/img-2_TxK9GgN.jfif": "Images/img-2_TxK9GgN.cb1bc54e7667.jfif", "Images/img-2_UcScsik.jfif": "Images/img-2_UcScsik.3bf05c122ba4.jfif", "Images/img-2_x3mtzZP.jfif": "Images/img-2_x3mtzZP.c4edcc0598e3.jfif", "Images/img-2_z08s05k.jfif": "Images/img-2_z08s05k.3e3309022b91.jfif", "Images/img-2_zf6g17b.jfif": "Images/img-2_zf6g17b.a98aa762f9e7.jfif", "Images/img-3.jfif": "Images/img-3.fa19403577c7.jfif", "Images/img-3_2vZP0s4.jfif": "Images/img-3_2vZP0s4.fa19403577c7.jfif", "Images/img-3_4w0q0Jv.jfif": "Images/img-3_4w0q0Jv.42b8a41aab33.jfif", "Images/img-3_6Mc6D1R.jfif": "Images/img-3_6Mc6D1R.ac8cacee2560.jfif", "Images/img-3_anqX0Wl.jfif": "Images/img-3_anqX0Wl.42b8a41aab33.jfif", "Images/img-3_aWaY4Cy.jfif": "Images/img-3_aWaY4Cy.fa19403577c7.jfif", "Images/img-3_bfpjhu5.jfif": "Images/img-3_bfpjhu5.9be4fb2414cd.jfif", "Images/img-3_cPSDGGd.jfif": "Images/img-3_cPSDGGd.42b8a41aab33.jfif", "Images/img-3_e2P5UhP.jfif": "Images/img-3_e2P5UhP.9be4fb2414cd.jfif", "Images/img-3_eadBef0.jfif": "Images/img-3_eadBef0.ac8cacee2560.jfif", "Images/img-3_g3emziQ.jfif": "Images/img-3_g3emziQ.ac8cacee2560.jfif", "Images/img-3_hCvm3ib.jfif": "Images/img-3_hCvm3ib.ac8cacee2560.jfif", "Images/img-3_IhdYerh.jfif": "Images/img-3_IhdYerh.fa19403577c7.jfif", "Images/img-3_lMekhIo.jfif": "Images/img-3_lMekhIo.5caf0079f041.jfif", "Images/img-3_mQ6DODt.jfif": "Images/img-3_mQ6DODt.5caf0079f041.jfif", "Images/img-3_OiErBQN.jfif": "Images/img-3_OiErBQN.9be4fb2414cd.jfif", "Images/img-3_QttQQ5q.jfif": "Images/img-3_QttQQ5q.5caf0079f041.jfif", "Images/img-3_RtOD4po.jfif": "Images/img-3_RtOD4po.fa19403577c7.jfif", "Images/img-3_tbqHE2p.jfif": "Images/img-3_tbqHE2p.5caf0079f041.jfif", "Images/img-3_wkOwEtH.jfif": "Images/img-3_wkOwEtH.9be4fb2414cd.jfif", "Images/img-3_wvBdAQ3.jfif": "Images/img-3_wvBdAQ3.42b8a41aab33.jfif", "Images/img-3_zGNwJWH.jfif": "Images/img-3_zGNwJWH.42b8a41aab33.jfif", "Images/img-4.jfif": "Images/img-4.5bd2fb1785d5.jfif", "Images/img-4_2035S2w.jfif": "Images/img-4_2035S2w.cbcbe8a6a5ec.jfif", "Images/img-4_2vFW5iz.jfif": "Images/img-4_2vFW5iz.5bd2fb1785d5.jfif", "Images/img-4_4cSTn8y.jfif": "Images/img-4_4cSTn8y.cbcbe8a6a5ec.jfif", "Images/img-4_7GruSzv.jfif": "Images/img-4_7GruSzv.57d9c61e5fb5.jfif", "Images/img-4_9Ylc9vW.jfif": "Images/img-4_9Ylc9vW.5bd2fb1785d5.jfif", "Images/img-4_CQoCAOA.jfif": "Images/img-4_CQoCAOA.217ecd28d106.jfif", "Images/img-4_g8SzH30.jfif": "Images/img-4_g8SzH30.57d9c61e5fb5.jfif", "Images/img-4_hRUtVzm.jfif": "Images/img-4_hRUtVzm.5bd2fb1785d5.jfif", "Images/img-4_jFuwlDa.jfif": "Images/img-4_jFuwlDa.f2bb5eb68026.jfif", "Images/img-4_JQtirhf.jfif": "Images/img-4_JQtirhf.5bd2fb1785d5.jfif", "Images/img-4_noEK6YP.jfif": "Images/img-4_noEK6YP.cbcbe8a6a5ec.jfif", "Images/img-4_OG7tUpR.jfif": "Images/img-4_OG7tUpR.f2bb5eb68026.jfif", "Images/img-4_oLFYtws.jfif": "Images/img-4_oLFYtws.217ecd28d106.jfif", "Images/img-4_PhKH9Il.jfif": "Images/img-4_PhKH9Il.f2bb5eb68026.jfif", "Images/img-4_sEq4CeA.jfif": "Images/img-4_sEq4CeA.217ecd28d106.jfif", "Images/img-4_x9nP3Sf.jfif": "Images/img-4_x9nP3Sf.cbcbe8a6a5ec.jfif", "Images/img-4_YR5wLdV.jfif": "Images/img-4_YR5wLdV.f2bb5eb68026.jfif", "Images/img-4_zpoBbUg.jfif": "Images/img-4_zpoBbUg.217ecd28d106.jfif", "Images/img-5.jfif": "Images/img-5.f14c0a340b17.jfif", "Images/img-5_1wPBFIK.jfif": "Images/img-5_1wPBFIK.092cefa4ab28.jfif", "Images/img-5_6SEReda.jfif": "Images/img-5_6SEReda.6e8bdf605f14.jfif", "Images/img-5_A2a07vy.jfif": "Images/img-5_A2a07vy.1982919f2578.jfif", "Images/img-5_accfRiH.jfif": "Images/img-5_accfRiH.1982919f2578.jfif", "Images/img-5_AN3kiM8.jfif": "Images/img-5_AN3kiM8.1a5180a3a442.jfif", "Images/img-5_bfb85uU.jfif": "Images/img-5_bfb85uU.6e8bdf605f14.jfif", "Images/img-5_cnNE9CN.jfif": "Images/img-5_cnNE9CN.1a5180a3a442.jfif", "Images/img-5_Ge9FQwI.jfif": "Images/img-5_Ge9FQwI.1a5180a3a442.jfif", "Images/img-5_JLNfwzc.jfif": "Images/img-5_JLNfwzc.f14c0a340b17.jfif", "Images/img-5_pgdRTq7.jfif": "Images/img-5_pgdRTq7.6e8bdf605f14.jfif", "Images/img-5_Pv56ZtG.jfif": "Images/img-5_Pv56ZtG.f14c0a340b17.jfif", "Images/img-5_QiwfWcb.jfif": "Images/img-5_QiwfWcb.f14c0a340b17.jfif", "Images/img-5_uaC3NSR.jfif": "Images/img-5_uaC3NSR.1982919f2578.jfif", "Images/img-5_v5Ts55N.jfif": "Images/img-5_v5Ts55N.1982919f2578.jfif", "Images/img-5_ve7wq31.jfif": "Images/img-5_ve7wq31.1982919f2578.jfif", "Images/img-5_VHFVO3R.jfif": "Images/img-5_VHFVO3R.092cefa4ab28.jfif", "Images/img-5_xE7jb6u.jfif": "Images/img-5_xE7jb6u.092cefa4ab28.jfif", "Images/img-5_yfMUcz8.jfif": "Images/img-5_yfMUcz8.092cefa4ab28.jfif", "Images/img-5_YJgg2mH.jfif": "Images/img-5_YJgg2mH.f14c0a340b17.jfif", "Images/img-6.jfif": "Images/img-6.94ed0e88f214.jfif", "Images/img-6.png": "Images/img-6.702f95cbb7b9.png", "Images/img-6_3jIDACh.jfif": "Images/img-6_3jIDACh.aab5f6a1725c.jfif", "Images/img-6_8ZvUAhA.jfif": "Images/img-6_8ZvUAhA.039850a81d5c.jfif", "Images/img-6_akXHPNz.jfif": "Images/img-6_akXHPNz.9c3fbd015842.jfif", "Images/img-6_cFz7Oix.jfif": "Images/img-6_cFz7Oix.9c3fbd015842.jfif", "Images/img-6_CNZvC4Z.jfif": "Images/img-6_CNZvC4Z.039850a81d5c.jfif", "Images/img-6_dUyGMQo.png": "Images/img-6_dUyGMQo.702f95cbb7b9.png", "Images/img-6_fYrginp.jfif": "Images/img-6_fYrginp.aab5f6a1725c.jfif", "Images/img-6_GJ8QMR6.png": "Images/img-6_GJ8QMR6.702f95cbb7b9.png", "Images/img-6_GRGX4kW.jfif": "Images/img-6_GRGX4kW.039850a81d5c.jfif", "Images/img-6_J58NMmT.jfif": "Images/img-6_J58NMmT.aab5f6a1725c.jfif", "Images/img-6_l7DsNZi.jfif": "Images/img-6_l7DsNZi.aab5f6a1725c.jfif", "Images/img-6_M8UWoLN.png": "Images/img-6_M8UWoLN.702f95cbb7b9.png", "Images/img-6_SdxbXAs.jfif": "Images/img-6_SdxbXAs.94ed0e88f214.jfif", "Images/img-6_sXE28sG.jfif": "Images/img-6_sXE28sG.94ed0e88f214.jfif", "Images/img-6_U3RXWM7.jfif": "Images/img-6_U3RXWM7.9c3fbd015842.jfif", "Images/img-6_W4VlCOS.jfif": "Images/img-6_W4VlCOS.94ed0e88f214.jfif", "Images/img-6_yjuDQE6.jfif": "Images/img-6_yjuDQE6.9c3fbd015842.jfif", "Images/img-6_yQ3ao87.jfif": "Images/img-6_yQ3ao87.9c3fbd015842.jfif", "Images/img-6_Z1b2BZy.png": "Images/img-6_Z1b2BZy.702f95cbb7b9.png", "Images/img-7.jfif": "Images/img-7.6bcf5edeedf0.jfif", "Images/img-7_1fqHaQn.jfif": "Images/img-7_1fqHaQn.6bcf5edeedf0.jfif", "Images/img-7_7dCDN5f.jfif": "Images/img-7_7dCDN5f.657c1e25d620.jfif", "Images/img-7_9MIKm2x.jfif": "Images/img-7_9MIKm2x.657c1e25d620.jfif", "Images/img-7_aHyHtaM.jfif": "Images/img-7_aHyHtaM.657c1e25d620.jfif", "Images/img-7_GrdgyKP.jfif": "Images/img-7_GrdgyKP.6bcf5edeedf0.jfif", "Images/img-7_hbXRMLo.jfif": "Images/img-7_hbXRMLo.d2ecea591f8a.jfif", "Images/img-7_q3fOwmk.jfif": "Images/img-7_q3fOwmk.ec6d887edad9.jfif", "Images/img-7_RA3fo5X.jfif": "Images/img-7_RA3fo5X.ec6d887edad9.jfif", "Images/img-7_WWHSIeN.jfif": "Images/img-7_WWHSIeN.d2ecea591f8a.jfif", "Images/img-7_xefgApH.jfif": "Images/img-7_xefgApH.6bcf5edeedf0.jfif", "Images/img-7_Y6AvH80.jfif": "Images/img-7_Y6AvH80.d2ecea591f8a.jfif", "Images/img-8.jfif": "Images/img-8.813c929b4d5b.jfif", "Images/img-8_8Qe9XHS.jfif": "Images/img-8_8Qe9XHS.813c929b4d5b.jfif", "Images/img-8_a9zEEHV.jfif": "Images/img-8_a9zEEHV.9fcafd01aac5.jfif", "Images/img-8_cG19hZb.jfif": "Images/img-8_cG19hZb.9fcafd01aac5.jfif", "Images/img-8_deMCH5T.jfif": "Images/img-8_deMCH5T.82d4f5b27300.jfif", "Images/img-8_JtxX9fN.jfif": "Images/img-8_JtxX9fN.82d4f5b27300.jfif", "Images/img-8_lNWllaw.jfif": "Images/img-8_lNWllaw.82d4f5b27300.jfif", "Images/img-8_mzeXtt6.jfif": "Images/img-8_mzeXtt6.813c929b4d5b.jfif", "Images/img-8_tTAIGVg.jfif": "Images/img-8_tTAIGVg.9fcafd01aac5.jfif", "Images/img-8_vioF0tN.jfif": "Images/img-8_vioF0tN.813c929b4d5b.jfif", "Images/img-8_Wrqldk7.jfif": "Images/img-8_Wrqldk7.82d4f5b27300.jfif", "Images/img-8_yxcp91l.jfif": "Images/img-8_yxcp91l.30276f6bbb29.jfif", "Images/img-8_zwDjKCb.jfif": "Images/img-8_zwDjKCb.30276f6bbb29.jfif", "Images/img-9.jfif": "Images/img-9.ae4c8814575b.jfif", "Images/img-9_3EAd7L8.jfif": "Images/img-9_3EAd7L8.ae4c8814575b.jfif", "Images/img-9_6wgYcwU.jfif": "Images/img-9_6wgYcwU.b88119f5ac06.jfif", "Images/img-9_b7Hg1rm.jfif": "Images/img-9_b7Hg1rm.614e7525b713.jfif", "Images/img-9_hXPzarO.jfif": "Images/img-9_hXPzarO.c3e7aca49c04.jfif", "Images/img-9_iFwAIQe.jfif": "Images/img-9_iFwAIQe.c3e7aca49c04.jfif", "Images/img-9_IHUiwo5.jfif": "Images/img-9_IHUiwo5.614e7525b713.jfif", "Images/img-9_jUEdsSL.jfif": "Images/img-9_jUEdsSL.b88119f5ac06.jfif", "Images/img-9_JXf02zA.jfif": "Images/img-9_JXf02zA.b88119f5ac06.jfif", "Images/img-9_kbSFhAL.jfif": "Images/img-9_kbSFhAL.ae4c8814575b.jfif", "Images/img-9_kewDOob.jfif": "Images/img-9_kewDOob.614e7525b713.jfif", "Images/img-9_nr8Bu3c.jfif": "Images/img-9_nr8Bu3c.c3e7aca49c04.jfif", "Images/img-9_nSWujoV.jfif": "Images/img-9_nSWujoV.b88119f5ac06.jfif", "Images/img-9_NUY0bUF.jfif": "Images/img-9_NUY0bUF.ae4c8814575b.jfif", "Images/img-9_qVbmbpS.jfif": "Images/img-9_qVbmbpS.ae4c8814575b.jfif", "Images/img-9_srIO7Xs.jfif": "Images/img-9_srIO7Xs.ae4c8814575b.jfif", "Images/img-9_WAoELnt.jfif": "Images/img-9_WAoELnt.614e7525b713.jfif", "Images/img-9_Zuf6fKk.jfif": "Images/img-9_Zuf6fKk.8350196406ec.jfif", "Images/muka.jpg": "Images/muka.4577b6627c8f.jpg", "Images/muka_axmIc0z.jpg": "Images/muka_axmIc0z.4577b6627c8f.jpg", "Images/muka_CRfd4J7.jpg": "Images/muka_CRfd4J7.4577b6627c8f.jpg", "Images/muka_eANKiOD.jpg": "Images/muka_eANKiOD.4577b6627c8f.jpg", "Images/muka_F5GvXO5.jpg": "Images/muka_F5GvXO5.4577b6627c8f.jpg", "Images/muka_ThiD38B.jpg": "Images/muka_ThiD38B.4577b6627c8f.jpg", "Images/muka_USrTT7P.jpg": "Images/muka_USrTT7P.4577b6627c8f.jpg", "Images/muka_YD80yCN.jpg": "Images/muka_YD80yCN.4577b6627c8f.jpg", "Images/muka_ZsnfOP7.jpg": "Images/muka_ZsnfOP7.4577b6627c8f.jpg", "Images/r1.jfif": "Images/r1.6723b06652c7.jfif", "Images/Reel_front.jfif": "Images/Reel_front.5fc9e329bfea.jfif", "Images/rod_slide.jfif": "Images/rod_slide.af005afcf3de.jfif", "js/cart.js": "js/cart.4f46d2012232.js", "js/product-filter.js": "js/product-filter.0f74abe4cbc4.js", "js/script.js": "js/script.e5dbcdf3dcf6.js"}, "version": "1.0"}